par2deep/__init__.py
par2deep/__main__.py
par2deep/cli.py
par2deep/gui_tk.py
par2deep/par2deep.png
par2deep/par2deep.py
par2deep/toolbox.py
par2deep/breeze/LICENSE
par2deep/breeze/breeze.tcl
par2deep/breeze/pkgIndex.tcl
par2deep/breeze/breeze/arrow-down-insens.gif
par2deep/breeze/breeze/arrow-down-prelight.gif
par2deep/breeze/breeze/arrow-down-small-insens.gif
par2deep/breeze/breeze/arrow-down-small-prelight.gif
par2deep/breeze/breeze/arrow-down-small.gif
par2deep/breeze/breeze/arrow-down.gif
par2deep/breeze/breeze/arrow-left-insens.gif
par2deep/breeze/breeze/arrow-left-prelight.gif
par2deep/breeze/breeze/arrow-left.gif
par2deep/breeze/breeze/arrow-right-insens.gif
par2deep/breeze/breeze/arrow-right-prelight.gif
par2deep/breeze/breeze/arrow-right.gif
par2deep/breeze/breeze/arrow-up-insens.gif
par2deep/breeze/breeze/arrow-up-prelight.gif
par2deep/breeze/breeze/arrow-up-small-insens.gif
par2deep/breeze/breeze/arrow-up-small-prelight.gif
par2deep/breeze/breeze/arrow-up-small.gif
par2deep/breeze/breeze/arrow-up.gif
par2deep/breeze/breeze/button-active.gif
par2deep/breeze/breeze/button-empty.gif
par2deep/breeze/breeze/button-focus.gif
par2deep/breeze/breeze/button-hover.gif
par2deep/breeze/breeze/button-insensitive.gif
par2deep/breeze/breeze/button-toggled.gif
par2deep/breeze/breeze/button.gif
par2deep/breeze/breeze/checkbox-checked-active.gif
par2deep/breeze/breeze/checkbox-checked-insensitive.gif
par2deep/breeze/breeze/checkbox-checked-pressed.gif
par2deep/breeze/breeze/checkbox-checked.gif
par2deep/breeze/breeze/checkbox-unchecked-active.gif
par2deep/breeze/breeze/checkbox-unchecked-insensitive.gif
par2deep/breeze/breeze/checkbox-unchecked-pressed.gif
par2deep/breeze/breeze/checkbox-unchecked.gif
par2deep/breeze/breeze/empty.gif
par2deep/breeze/breeze/entry-active.gif
par2deep/breeze/breeze/entry-focus.gif
par2deep/breeze/breeze/entry-insensitive.gif
par2deep/breeze/breeze/entry.gif
par2deep/breeze/breeze/labelframe.gif
par2deep/breeze/breeze/notebook-client.gif
par2deep-1.11.0.dist-info/LICENSE
par2deep-1.11.0.dist-info/METADATA
par2deep-1.11.0.dist-info/WHEEL
par2deep-1.11.0.dist-info/entry_points.txt
par2deep-1.11.0.dist-info/top_level.txt
par2deep-1.11.0.dist-info/RECORD
