Metadata-Version: 2.1
Name: par2deep
Version: 1.11.0
Summary: Produce, verify and repair par2 files recursively.
Author: Brent Huisman
Author-email: brent@huisman.pl
Maintainer-email: Brent Huisman <brent@huisman.pl>
License:                    GNU LESSER GENERAL PUBLIC LICENSE
Project-URL: homepage, https://github.com/brenthuisman/par2deep
Project-URL: documentation, https://github.com/brenthuisman/par2deep
Project-URL: repository, https://github.com/brenthuisman/par2deep
Project-URL: changelog, https://github.com/brenthuisman/par2deep/blob/master/README.md
Keywords: par2,file,integrity
Classifier: Development Status :: 5 - Production/Stable
Classifier: License :: OSI Approved :: GNU Lesser General Public License v3 or later (LGPLv3+)
Classifier: Programming Language :: Python :: 3
Classifier: Environment :: Console
Classifier: Environment :: MacOS X
Classifier: Environment :: Win32 (MS Windows)
Classifier: Environment :: X11 Applications
Classifier: Operating System :: MacOS :: MacOS X
Classifier: Operating System :: Microsoft :: Windows
Classifier: Operating System :: POSIX
Classifier: Operating System :: Unix
Classifier: Topic :: Utilities
Classifier: Operating System :: OS Independent
Requires-Python: >=3.8
License-File: LICENSE
Requires-Dist: darkdetect
Requires-Dist: tqdm
Requires-Dist: configargparse
Requires-Dist: send2trash
Requires-Dist: par2cmdline-turbo
